morphcp/__init__ 2.py
morphcp/__init__.py
morphcp/create_env 2.py
morphcp/create_env 3.py
morphcp/create_env.py
morphcp/morphclass 2.py
morphcp/morphclass.py
morphcp/vars 2.py
morphcp/vars.py
morphcp/inject/__init__.py
morphcp/inject/components 2.py
morphcp/inject/components 3.py
morphcp/inject/components.py
morphcp/logging/__init__.py
morphcp/logging/loghandler.py
morphcp/tenants/__init__.py
morphcp/tenants/manage_tenant 2.py
morphcp/tenants/manage_tenant.py
morphcp/utils/__init__.py
morphcp/utils/helpers.py
morphcp-0.0.22.dist-info/LICENSE.txt
morphcp-0.0.22.dist-info/METADATA
morphcp-0.0.22.dist-info/WHEEL
morphcp-0.0.22.dist-info/top_level.txt
morphcp-0.0.22.dist-info/RECORD
