Metadata-Version: 2.1
Name: morphcp
Version: 0.0.22
Summary: Tool utilized to deploy content into a morpheus appliance
Home-page: https://gitlab.com/jaredlutgen/morphcp
Author: Jared Lutgen
Author-email: jlutgen@morpheusdata.com
License: MIT
Classifier: Development Status :: 4 - Beta
Classifier: License :: OSI Approved :: MIT License
Classifier: Programming Language :: Python
Classifier: Programming Language :: Python :: 3.5
Classifier: Programming Language :: Python :: 3.6
Classifier: Topic :: Software Development :: Libraries
Classifier: Topic :: Software Development :: Libraries :: Python Modules
Classifier: Intended Audience :: Developers
Requires-Python: >=3.5
License-File: LICENSE.txt
Requires-Dist: requests
